application/__init__.py
configs/__init__.py
configs/__version__.py
yangxian-1.1.dist-info/METADATA
yangxian-1.1.dist-info/WHEEL
yangxian-1.1.dist-info/top_level.txt
yangxian-1.1.dist-info/RECORD
