Metadata-Version: 2.1
Name: yangxian
Version: 1.1
Summary: all in here
Home-page: https://gitee.com/mlste/yangxian
Author: LongGengYung
Author-email: yonglonggeng@63.com
License: UNKNOWN
Platform: UNKNOWN
Classifier: Development Status :: 5 - Production/Stable
Classifier: Intended Audience :: Developers
Classifier: Natural Language :: English
Classifier: Programming Language :: Python
Classifier: Programming Language :: Python :: 3
Classifier: Programming Language :: Python :: 3.4
Classifier: Programming Language :: Python :: 3.5
Classifier: Programming Language :: Python :: 3.6
Classifier: Programming Language :: Python :: 3.7
Classifier: Programming Language :: Python :: Implementation :: CPython
Classifier: Programming Language :: Python :: Implementation :: PyPy
Requires-Python: >=3.0, !=3.0.*, !=3.1.*, !=3.2.*, !=3.3*
Requires-Dist: py2neo (==2020.1.0)
